{"info":{"title":"API - toolbox-fullstack-test-api","version":"1.0.0","description":"Documentación de API toolbox-fullstack-test-api"},"host":"localhost:10001","schemes":["http","https"],"swagger":"2.0","paths":{"/iecho":{"get":{"summary":"Invierte un texto","description":"Se le envía un texto y responde con el mismo texto invertido","tags":["IECHO"],"parameters":[{"$ref":"#/parameters/textQuery"}],"responses":{"200":{"description":"Ok"},"400":{"description":"Parámetros inválidos."}}}}},"definitions":{},"responses":{},"parameters":{"textQuery":{"in":"query","name":"text","description":"Texto a invertir","type":"string"}},"securityDefinitions":{},"tags":[]}